{ "objects": [
   { "id":"100", "value":null, "link":null }, { "id":"100", "value":null, "link":null }, { "id":"100", "value":null, "link":null }, { "id":"100", "value":null, "link":null },{ "id":"100", "value":null, "link":null },
   { "id":"100", "value":null, "link":null }, { "id":"100", "value":null, "link":null }, { "id":"100", "value":null, "link":null }, { "id":"100", "value":null, "link":null },{ "id":"100", "value":null, "link":null },
   { "id":"100", "value":null, "link":null }, { "id":"100", "value":null, "link":null }, { "id":"100", "value":null, "link":null }, { "id":"100", "value":null, "link":null },{ "id":"100", "value":null, "link":null },
   { "id":"100", "value":null, "link":null }, { "id":"100", "value":null, "link":null }, { "id":"100", "value":null, "link":null }, { "id":"100", "value":null, "link":null },{ "id":"100", "value":null, "link":null },
   { "id":"100", "value":null, "link":null }, { "id":"100", "value":null, "link":null }, { "id":"100", "value":null, "link":null }, { "id":"100", "value":null, "link":null },{ "id":"100", "value":null, "link":null }
] }